Metadata-Version: 2.1
Name: areenpackage
Version: 1.0.0
Summary: This is a package that contains the basic mathematical functions like addition,subtract and multiplication
Home-page: https://github.com/areen-patil/areen_python_package
Author: Areen Patil
Author-email: Areen.Patil@iiitb.ac.in
